jarvis/__init__.py
jarvis/tools/__init__.py
jarvis/train/__init__.py
jarvis/train/box/__init__.py
jarvis/train/box/box.py
jarvis/train/client/__init__.py
jarvis/train/client/client.py
jarvis/train/custom/__init__.py
jarvis/train/custom/custom.bak.py
jarvis/train/custom/custom.py
jarvis/train/datasets/__init__.py
jarvis/train/datasets/datasets.py
jarvis/train/models/__init__.py
jarvis/train/models/models.py
jarvis/train/models/parser.py
jarvis/train/models/trained.py
jarvis/train/params/__init__.py
jarvis/train/params/params.py
jarvis/utils/__init__.py
jarvis/utils/arrays/__init__.py
jarvis/utils/datasets/__init__.py
jarvis/utils/datasets/datasets.py
jarvis/utils/db/__init__.py
jarvis/utils/db/db.py
jarvis/utils/db/funcs.py
jarvis/utils/db/query.py
jarvis/utils/display/__init__.py
jarvis/utils/display/imshow.py
jarvis/utils/display/montage.py
jarvis/utils/general/__init__.py
jarvis/utils/general/base.py
jarvis/utils/general/cuda.py
jarvis/utils/general/file.py
jarvis/utils/general/gpus.py
jarvis/utils/general/hasher.py
jarvis/utils/general/nodes.py
jarvis/utils/general/overload.py
jarvis/utils/general/printer.py
jarvis/utils/general/profiler.py
jarvis/utils/general/rdict.py
jarvis/utils/general/script.py
jarvis/utils/general/tools.py
jarvis/utils/io/__init__.py
jarvis/utils/io/main.py
jarvis/utils/io/parser_hdf5.py
jarvis/utils/io/parser_json.py
jarvis/utils/io/parser_npy.py
jarvis/utils/io/plugins.py
jarvis/utils/io/utils.py
jarvis/utils/math/__init__.py
jarvis/utils/math/ops.py
jarvis_md-0.0.1a17.dist-info/LICENSE
jarvis_md-0.0.1a17.dist-info/METADATA
jarvis_md-0.0.1a17.dist-info/WHEEL
jarvis_md-0.0.1a17.dist-info/entry_points.txt
jarvis_md-0.0.1a17.dist-info/top_level.txt
jarvis_md-0.0.1a17.dist-info/RECORD
