Metadata-Version: 2.1
Name: jarvis-md
Version: 0.0.1a17
Summary: Data science and deep learning tools for healthcare
Home-page: https://github.com/peterchang77/jarvis-core
Author: Peter D. Chang
Author-email: pchang077@gmail.com
License: UNKNOWN
Platform: UNKNOWN
Classifier: Development Status :: 3 - Alpha
Classifier: Intended Audience :: Developers
Classifier: License :: OSI Approved :: GNU General Public License v3 (GPLv3)
Classifier: Programming Language :: Python :: 3.6
Classifier: Programming Language :: Python :: 3.7
Classifier: Programming Language :: Python :: 3.8
Classifier: Programming Language :: Python :: 3.9
Requires-Python: >=3.6
Requires-Dist: pyyaml (>=5.2)
Requires-Dist: requests
Requires-Dist: h5py
Requires-Dist: numpy
Requires-Dist: pandas
Requires-Dist: scipy
Requires-Dist: matplotlib
